README.md
setup.py
kubega/__init__.py
kubega/_signal.py
kubega/allreduce.py
kubega/allreduce_test.py
kubega/checkpoint.py
kubega/checkpoint_test.py
kubega/collective.py
kubega/collective_test.py
kubega/conftest.py
kubega/env.py
kubega/goodput.py
kubega/goodput_test.py
kubega/sched_hints.py
kubega/utils.py
kubega.egg-info/PKG-INFO
kubega.egg-info/SOURCES.txt
kubega.egg-info/dependency_links.txt
kubega.egg-info/requires.txt
kubega.egg-info/top_level.txt
kubega/torch/__init__.py
kubega/torch/_metrics.py
kubega/torch/_metrics_test.py
kubega/torch/accumulator.py
kubega/torch/accumulator_test.py
kubega/torch/adaptive_bptt_iterator.py
kubega/torch/data.py
kubega/torch/data_test.py
kubega/torch/epoch.py
kubega/torch/epoch_test.py
kubega/torch/gradient_noise_scale.py
kubega/torch/gradient_noise_scale_test.py
kubega/torch/parallel.py
kubega/torch/parallel_test.py
kubega/torch/scaling_rules.py
kubega/torch/scaling_rules_test.py